{
  "schemaVersion": 1,
  "repository": "kotoba-tech/dotsu-ota-test",
  "platform": "android",
  "versions": {
    "1.4.6": {
      "otaVersion": 342678459,
      "releaseId": 342678459,
      "releaseTag": "test/0.0.45",
      "releaseName": "OTA Update android v1.4.6",
      "publishedAt": "2026-06-22T04:46:55Z",
      "assetId": 454231199,
      "assetName": "android-1.4.6.zip",
      "assetSize": 6120454,
      "downloadUrl": "https://github.com/kotoba-tech/dotsu-ota-test/releases/download/test/0.0.45/android-1.4.6.zip"
    }
  }
}
